urlp/__init__.py
urlp/__main__.py
urlp/cli.py
urlp-0.0.3.dist-info/METADATA
urlp-0.0.3.dist-info/WHEEL
urlp-0.0.3.dist-info/entry_points.txt
urlp-0.0.3.dist-info/top_level.txt
urlp-0.0.3.dist-info/RECORD
