Metadata-Version: 2.1
Name: urlp
Version: 0.0.3
Summary: A simple command-line utility for parsing URLs.
Home-page: https://github.com/yangxuhui/urlp
Author: Xuhui Yang
Author-email: yangxuhui1992@163.com
License: UNKNOWN
Keywords: url parse command-line
Platform: UNKNOWN
Classifier: Development Status :: 3 - Alpha
Classifier: Intended Audience :: Developers
Classifier: Topic :: Utilities
Classifier: License :: OSI Approved :: BSD License
Classifier: Programming Language :: Python :: 2
Classifier: Programming Language :: Python :: 2.7
Classifier: Programming Language :: Python :: 3
Classifier: Programming Language :: Python :: 3.5
Classifier: Programming Language :: Python :: 3.6
Classifier: Programming Language :: Python :: 3.7
Requires-Python: >=2.7, !=3.0.*, !=3.1.*, !=3.2.*, !=3.3.*, !=3.4.*, <4
Requires-Dist: tldextract
